{
  "name": "{{ doc.codeName | linebreak }}",
  "source": "{{ doc.outputPath }}",
  "description": "{{doc.description}}",
  {% if doc.params %}
  "params": [
    {% for param in doc.params %}
      {
        "name": "{{param.name | replace('`','')}}",
        "description": "{{param.description | replace('`','')}}",
        "typeList": "{{param.typeList}}"
      }{% if loop.last != true %},{% endif %}
    {% endfor %}
  ],
  {% endif %}
  "returns": {
    "typeList": "{{doc.returns.typeList}}",
    "description": "{{doc.returns.description}}"
  },
  "example": "{{doc.example}}"
}